{
  "name": "late s",
  "running_style": 2,
  "learn_skill_list": [
    [
      "Calm and Collected",
      "Dazzling Disorientation",
      "Determined Descent",
      "Disorient",
      "Gourmand",
      "Head-On",
      "Hydrate",
      "Neck and Neck",
      "Pace Chaser Corners ○",
      "Pace Chaser Savvy ○",
      "Pace Chaser Straightaways ○",
      "Preferred Position",
      "Prepared to Pass",
      "Race Planner",
      "Shatterproof",
      "Shrewd Step",
      "Speed Star",
      "Stamina to Spare",
      "Straight Descent",
      "Tactical Tweak",
      "Technician",
      "Adored by All",
      "Blinding Flash",
      "Countermeasure",
      "Gap Closer",
      "Huge Lead",
      "In High Spirits",
      "Intimidate",
      "Light as a Feather",
      "Meticulous Measures",
      "Perfect Prep!",
      "Plan X",
      "Sprint Corners ○",
      "Sprint Straightaways ○",
      "Sprinting Gear",
      "Staggering Lead",
      "Stop Right There!",
      "Turbo Sprint",
      "Wait-and-See",
      "You've Got No Shot",
      "Cloudy Days ○",
      "Firm Conditions ○",
      "Kokura Racecourse ○",
      "Kyoto Racecourse ○",
      "Inner Post Proficiency ○",
      "Hakodate Racecourse ○",
      "Hanshin Racecourse ○",
      "Lone Wolf",
      "Left-Handed ○",
      "Lucky Seven",
      "Non-Standard Distance ○",
      "Outer Post Proficiency ○",
      "Right-Handed ○",
      "Snowy Days ○",
      "Spring Runner ○",
      "Standard Distance ○",
      "Summer Runner ○"
    ]
  ],
  "learn_skill_blacklist": [
    "Spring Runner ◎",
    "Standard Distance ◎",
    "Summer Runner ◎",
    "Target in Sight ◎",
    "Tokyo Racecourse ◎",
    "Wet Conditions ◎",
    "Winter Runner ◎",
    "Snowy Days ◎",
    "Sapporo Racecourse ◎",
    "Rainy Days ◎",
    "Right-Handed ◎",
    "Pace Chaser Savvy ◎",
    "Pace Chaser Corners ◎",
    "Pace Chaser Straightaways ◎",
    "Sprint Straightaways ◎",
    "Sprint Corners ◎"
  ],
  "extra_race_list": [
    100629,
    100630,
    100632,
    100633,
    100635,
    100623,
    100625,
    200183,
    200171,
    200162,
    200164,
    200165,
    200074,
    200109,
    200085,
    200167,
    200077,
    300006,
    300003,
    300008,
    300009,
    300029,
    300033,
    300005,
    300073,
    300074,
    300109,
    300088,
    300076,
    300077,
    300079,
    200078
  ],
  "learn_skill_threshold": 2000,
  "target_distance": 1,
  "auto_buy_override_threshold": false,
  "mandatory_skill_list": [
    "Ramp Up",
    "It's On!",
    "Homestretch Haste",
    "Professor of Curvature",
    "Tail Held High"
  ],
  "stat_priority": [
    0,
    2,
    4,
    3,
    1
  ],
  "stat_ideal_targets": [
    1200,
    600,
    1200,
    900,
    1000
  ],
  "stat_min_targets": [
    1200,
    600,
    900,
    600,
    900
  ]
}